arch_flow/ArchFlow.py
arch_flow/ArchFlowCli.py
arch_flow/DirectoryCreator.py
arch_flow/DirectoryExplorer.py
arch_flow/Run.py
arch_flow/StringManipulator.py
arch_flow/__init__.py
arch_flow/db.json
arch_flow/exceptions/ExceptionHandler.py
arch_flow/exceptions/FileOrDirectoryExistsError.py
arch_flow/exceptions/NotFoundException.py
arch_flow/implementations/DirectoryCreatorImplementation.py
arch_flow/implementations/DirectoryExplorerImplementation.py
arch_flow/implementations/StringManipulatorImplementation.py
arch_flow/output/OutputHandler.py
arch_flow/utils/DirectoryExplorerUtil.py
arch_flow/utils/Filter.py
arch_flow-0.1.8.2.dist-info/LICENCE
arch_flow-0.1.8.2.dist-info/METADATA
arch_flow-0.1.8.2.dist-info/WHEEL
arch_flow-0.1.8.2.dist-info/top_level.txt
arch_flow-0.1.8.2.dist-info/RECORD
