Metadata-Version: 2.1
Name: arch-flow
Version: 0.1.8.2
Summary: O ArchFlow é uma plataforma de código aberto projetada para simplificar o desenvolvimento de automações.
Author: Carlos Vinicius Da Silva
Author-email: vini989073599@gmail.com
License: MIT License
Keywords: arch flow
License-File: LICENCE
Requires-Dist: colorama
Requires-Dist: rich
